mygrads/__init__.py
mygrads-0.0.3.dist-info/LICENSE
mygrads-0.0.3.dist-info/METADATA
mygrads-0.0.3.dist-info/WHEEL
mygrads-0.0.3.dist-info/top_level.txt
mygrads-0.0.3.dist-info/RECORD
