Metadata-Version: 2.1
Name: mygrads
Version: 0.0.3
Summary: A set of GrADS functions in Python.
Home-page: https://github.com/davidmnielsen/mygrads
Author: David Nielsen
Author-email: davidnielsen@id.uff.br
License: UNKNOWN
Platform: UNKNOWN
Classifier: Programming Language :: Python :: 3
Classifier: License :: OSI Approved :: MIT License
Classifier: Operating System :: OS Independent
Requires-Dist: numpy
Requires-Dist: matplotlib
Requires-Dist: xarray
Requires-Dist: cartopy
